validation/__init__.py
validation/add_custom_metric.py
validation/create_custom_metrics.py
validation/custom_metrics.py
validation/diff_tool.py
validation/manage_metrics.py
validation/metrics.py
validation/script.py
validation/validate.py
evalTool-0.1.dist-info/LICENSE
evalTool-0.1.dist-info/METADATA
evalTool-0.1.dist-info/WHEEL
evalTool-0.1.dist-info/entry_points.txt
evalTool-0.1.dist-info/top_level.txt
evalTool-0.1.dist-info/RECORD
